collective.zopeconsul-0.3-py3.10-nspkg.pth
collective/zopeconsul/__init__.py
collective/zopeconsul/configure.zcml
collective/zopeconsul/consulserver.py
collective/zopeconsul/startup.py
collective/zopeconsul/vhm.py
collective.zopeconsul-0.3.dist-info/METADATA
collective.zopeconsul-0.3.dist-info/WHEEL
collective.zopeconsul-0.3.dist-info/entry_points.txt
collective.zopeconsul-0.3.dist-info/namespace_packages.txt
collective.zopeconsul-0.3.dist-info/top_level.txt
collective.zopeconsul-0.3.dist-info/RECORD
