Metadata-Version: 2.1
Name: collective.zopeconsul
Version: 0.3
Summary: Asynchronous updating of consul with zope configration
Home-page: https://github.com/collective/collective.zopeconsul/
Author: Dylan Jay, Jon Pentland
Author-email: software@pretaweb.com
License: GPL
Classifier: Development Status :: 4 - Beta
Classifier: Environment :: Web Environment
Classifier: Framework :: Plone
Classifier: Framework :: Plone :: 4.3
Classifier: Framework :: Plone :: 5.0
Classifier: License :: OSI Approved :: GNU General Public License v2 (GPLv2)
Classifier: Programming Language :: Python
Classifier: Programming Language :: Python :: 2.7
Classifier: Topic :: Internet :: WWW/HTTP
Classifier: Topic :: Internet :: WWW/HTTP :: Dynamic Content
Classifier: Topic :: Software Development :: Libraries :: Python Modules
Requires-Dist: setuptools
Requires-Dist: Zope2
Requires-Dist: python-consul
Requires-Dist: collective.monkeypatcher
Requires-Dist: zope.app.publication
Provides-Extra: test
Requires-Dist: plone.app.testing; extra == "test"
Requires-Dist: plone.app.robotframework>=0.7.0rc4; extra == "test"
